rate_limiter/__init__.py
rate_limiter/exceptions.py
rate_limiter/rate_limiter.py
tests/__init__.py
tests/test_rate_limiter.py
leakyBucket_limiter-0.1.0.dist-info/METADATA
leakyBucket_limiter-0.1.0.dist-info/WHEEL
leakyBucket_limiter-0.1.0.dist-info/top_level.txt
leakyBucket_limiter-0.1.0.dist-info/RECORD
