Metadata-Version: 2.1
Name: leakyBucket-limiter
Version: 0.1.0
Summary: A simple rate limitter using redis
Home-page: https://github.com/sarmaasis/rate-limiter
Author: Ashish Sharma
Author-email: sarmaassis@gmail.com
License: UNKNOWN
Platform: UNKNOWN
Classifier: Programming Language :: Python :: 3
Classifier: License :: OSI Approved :: MIT License
Classifier: Operating System :: OS Independent
Requires-Python: >3.8
Requires-Dist: redis
